[
  {
    "id": "wedding-floral-strip",
    "name": "Wedding Floral (3 Poses)",
    "thumbnail": "/assets/frames/birthday.png",
    "frameSrc": "/assets/frames/birthday.png",
    "slots": [
      {"x":186,"y":231,"w":822,"h":393},
      {"x":186,"y":648,"w":819,"h":399},
      {"x":186,"y":1068,"w":822,"h":246}
    ]
  },
  {
    "id": "blue-jeans",
    "name": "Blue Jeans",
    "thumbnail": "/public/assets/thumbnails/blue-jeans.jpg",
    "frameSrc": "/public/assets/frames/blue-jeans.png",
    "slots": [
      {"x": 42, "y": 354, "w": 513, "h": 360},
      {"x": 42, "y": 780, "w": 513, "h": 360},
      {"x": 42, "y": 1206, "w": 513, "h": 360},
      {"x": 639, "y": 1209, "w": 513, "h": 360},
      {"x": 636, "y": 780, "w": 513, "h": 360},
      {"x": 642, "y": 354, "w": 513, "h": 360}
    ]
  },
  {
    "id": "weeding-1",
    "name": "Weeding Theme 1",
    "thumbnail": "/public/assets/thumbnails/weeding_1.jpg",
    "frameSrc": "/public/assets/frames/weeding_1.png",
    "slots": [
      {"x": 147, "y": 99, "w": 927, "h": 543},
      {"x": 144, "y": 657, "w": 945, "h": 543}
    ]
  }
]

